Izmon/Main.py
Izmon/__init__.py
Izmon/setup.py
Izmon/Class/Dictionary.py
Izmon/Class/Gym.py
Izmon/Class/Set.py
Izmon/Class/__init__.py
Izmon/Class/setup.py
Izmon/Class/Basic/Common_Function.py
Izmon/Class/Basic/Common_Variable.py
Izmon/Class/Basic/Settings.py
Izmon/Class/Basic/__init__.py
Izmon/Class/Battle/Battle.py
Izmon/Class/Battle/Battle_Caluculate.py
Izmon/Class/Battle/Battle_Other.py
Izmon/Class/Battle/Battle_Set.py
Izmon/Class/Battle/__init__.py
Izmon/Class/CloudSave/Common.py
Izmon/Class/CloudSave/Download.py
Izmon/Class/CloudSave/Upload.py
Izmon/Class/CloudSave/__init__.py
Izmon/Class/Events/Events_Latest.py
Izmon/Class/Events/Events_Passed.py
Izmon/Class/Events/__init__.py
Izmon/Class/Save_Code/Decode.py
Izmon/Class/Save_Code/Encode.py
Izmon/Class/Save_Code/__init__.py
Izmon/Class/Start_End/End.py
Izmon/Class/Start_End/Start.py
Izmon/Class/Start_End/__init__.py
Izmon-1.1.2.dist-info/LICENSE.txt
Izmon-1.1.2.dist-info/METADATA
Izmon-1.1.2.dist-info/WHEEL
Izmon-1.1.2.dist-info/top_level.txt
Izmon-1.1.2.dist-info/RECORD
