Metadata-Version: 2.1
Name: Izmon
Version: 1.1.2
Summary: You can play Izmon with this libraly.
Home-page: https://github.com/akita0724
Author: Yohei Akita, nabe, miso
Author-email: akita.yohei0724@gmail.com
License: GPL v2.0
Keywords: Izmon
Classifier: Programming Language :: Python :: 3 :: Only
Classifier: License :: OSI Approved :: GNU General Public License v2 (GPLv2)
Classifier: Operating System :: OS Independent
Requires: requests
Requires-Python: >=3.7
License-File: LICENSE.txt
